flyingcircus/__init__.py
flyingcircus/_about.py
flyingcircus/_raw/__init__.py
flyingcircus/_raw/accessanalyzer.py
flyingcircus/_raw/amazonmq.py
flyingcircus/_raw/amplify.py
flyingcircus/_raw/apigateway.py
flyingcircus/_raw/apigatewayv2.py
flyingcircus/_raw/applicationautoscaling.py
flyingcircus/_raw/appmesh.py
flyingcircus/_raw/appstream.py
flyingcircus/_raw/appsync.py
flyingcircus/_raw/athena.py
flyingcircus/_raw/autoscaling.py
flyingcircus/_raw/autoscalingplans.py
flyingcircus/_raw/backup.py
flyingcircus/_raw/batch.py
flyingcircus/_raw/budgets.py
flyingcircus/_raw/certificatemanager.py
flyingcircus/_raw/cloud9.py
flyingcircus/_raw/cloudformation.py
flyingcircus/_raw/cloudfront.py
flyingcircus/_raw/cloudtrail.py
flyingcircus/_raw/cloudwatch.py
flyingcircus/_raw/codebuild.py
flyingcircus/_raw/codecommit.py
flyingcircus/_raw/codedeploy.py
flyingcircus/_raw/codepipeline.py
flyingcircus/_raw/codestar.py
flyingcircus/_raw/codestarnotifications.py
flyingcircus/_raw/cognito.py
flyingcircus/_raw/config.py
flyingcircus/_raw/datapipeline.py
flyingcircus/_raw/dax.py
flyingcircus/_raw/directoryservice.py
flyingcircus/_raw/dlm.py
flyingcircus/_raw/dms.py
flyingcircus/_raw/docdb.py
flyingcircus/_raw/dynamodb.py
flyingcircus/_raw/ec2.py
flyingcircus/_raw/ecr.py
flyingcircus/_raw/ecs.py
flyingcircus/_raw/efs.py
flyingcircus/_raw/eks.py
flyingcircus/_raw/elasticache.py
flyingcircus/_raw/elasticbeanstalk.py
flyingcircus/_raw/elasticloadbalancing.py
flyingcircus/_raw/elasticloadbalancingv2.py
flyingcircus/_raw/elasticsearch.py
flyingcircus/_raw/emr.py
flyingcircus/_raw/events.py
flyingcircus/_raw/eventschemas.py
flyingcircus/_raw/fsx.py
flyingcircus/_raw/gamelift.py
flyingcircus/_raw/glue.py
flyingcircus/_raw/greengrass.py
flyingcircus/_raw/guardduty.py
flyingcircus/_raw/iam.py
flyingcircus/_raw/inspector.py
flyingcircus/_raw/iot.py
flyingcircus/_raw/iot1click.py
flyingcircus/_raw/iotanalytics.py
flyingcircus/_raw/iotevents.py
flyingcircus/_raw/iotthingsgraph.py
flying_circus-0.7.3.dist-info/LICENSE
flying_circus-0.7.3.dist-info/WHEEL
flying_circus-0.7.3.dist-info/METADATA
flying_circus-0.7.3.dist-info/RECORD
