Metadata-Version: 2.1
Name: flying-circus
Version: 0.7.3
Summary: A tool for describing AWS infrastructure as code
Home-page: https://github.com/garyd203/flying-circus
License: LGPL-3.0
Keywords: AWS,cloudformation,infrastructure-as-code
Author: Gary Donovan
Author-email: gazza@gazza.id.au
Requires-Python: >=3.6,<4.0
Classifier: Development Status :: 4 - Beta
Classifier: Intended Audience :: Developers
Classifier: License :: OSI Approved :: GNU Lesser General Public License v3 (LGPLv3)
Classifier: Natural Language :: English
Classifier: Operating System :: OS Independent
Classifier: Programming Language :: Python
Classifier: Programming Language :: Python :: 3
Classifier: Programming Language :: Python :: 3.6
Classifier: Programming Language :: Python :: 3.7
Classifier: Programming Language :: Python :: 3.8
Classifier: Topic :: Software Development :: Pre-processors
Classifier: Topic :: System :: Systems Administration
Requires-Dist: PyYAML (>=5.1.1,<5.2.0)
Requires-Dist: attrs (>=18.2.0,<19.0.0)
Requires-Dist: inflection (>=0.3.1,<0.4.0)
Project-URL: Documentation, https://flying-circus.readthedocs.io/en/latest/
Project-URL: Repository, https://github.com/garyd203/flying-circus
